autorootcwd/__init__.py
autorootcwd-1.0.1.dist-info/METADATA
autorootcwd-1.0.1.dist-info/WHEEL
autorootcwd-1.0.1.dist-info/top_level.txt
autorootcwd-1.0.1.dist-info/RECORD
