Metadata-Version: 2.1
Name: autorootcwd
Version: 1.0.1
Summary: Simple package for easy project root setup
Home-page: https://github.com/ashleve/autoroot
Author: Łukasz Zalewski
Author-email: lukasz.zalewski.ai@gmail.com
License: MIT
Requires-Python: >=3.8.0
Requires-Dist: python-dotenv >=0.20.0
Requires-Dist: pyrootutils >=1.0.4
